{"question": "In fourth grade there were 4 students at the start of the year. During the year 3 students left and 42 new students came to school. How many students were in fourth grade at the end?", "qid": "193", "response": "To solve this problem, we need to find the difference between the number of students at the start and the number of students at the end.\n\nAt the start of the year, there were 4 students in fourth grade.\nAt the end of the year, there were 42 new students, making a total of 42 + 4 = 46 students.\n\nThe difference between the number of students at the start and the number of students at the end is 46 - 4 = 42 students.\n\nThe answer is 42 students.", "answer": 43, "correct": false, "image": "images/mawpsmultiarith/193.png"}