{"question": "John made 6 dollars mowing lawns and 18 dollars weed eating. If he only spent 3 dollar a week, how long would the money last him?", "qid": "316", "response": "To solve this problem, we need to find out how much money John has in total and how much he spends per week.\n\nJohn made 6 dollars mowing lawns and 18 dollars weed eating, so he has a total of 6 + 18 = 24 dollars.\n\nHe spends 3 dollars per week, so we need to find out how many weeks this money will last him.\n\nTo do this, we can divide the total amount of money by the weekly expense: 24 / 3 = 8 weeks.\n\nThe answer is 8 weeks.", "answer": 8, "correct": true, "image": "images/mawpsmultiarith/316.png"}