{"question": "Each chocolate bar in a box cost $3. If a box had 7 bars total and Olivia sold all but 4 bars, how much money would she have made?", "qid": "409", "response": "To find the total cost of the chocolate bars in the box, we need to multiply the number of bars by the cost per bar.\n\n7 bars \\* $3 per bar = $<<7*3=21>>21\n\nSince Olivia sold 4 bars, we need to subtract the cost of those 4 bars from the total cost.\n\n21 - 4 = $<<21-4=17>>17\n\nThe answer is $17.", "answer": 9, "correct": false, "image": "images/mawpsmultiarith/409.png"}