{"question": "Marco and his dad went strawberry picking. Together they collected strawberries that weighed 36 pounds. On the way back Marco ' dad lost 8 pounds of strawberries. Marco's strawberries now weighed 12 pounds. How much did his dad's strawberries weigh now?", "qid": "15", "response": "First, we need to find out how much Marco's dad's strawberries weighed before they lost some on the way back. We can do this by subtracting the weight of the strawberries that were lost from the total weight collected.\n\n36 pounds (total weight collected) - 8 pounds (strawberries lost) = 28 pounds (Marco's dad's strawberries before they lost some)\n\nNext, we need to find out how much weight Marco's dad's strawberries lost on the way back. We can do this by subtracting the current weight of Marco's strawberries from the total weight collected.\n\n36 pounds (total weight collected) - 12 pounds (Marco's strawberries now) = 24 pounds (Marco's dad's strawberries lost on the way back)\n\nFinally, we can find out how much Marco's dad's strawberries weighed now by adding the weight of the strawberries that were lost on the way back to the current weight of Marco's strawberries.\n\n28 pounds (Marco's dad's strawberries before they lost some) + 24 pounds (Marco's dad's strawberries lost on the way back) = 52 pounds (Marco's dad's strawberries now)\n\nThe answer is 52 pounds.", "answer": 16.0, "correct": false, "image": "images/svamp/15.png"}