{"question": "There are some baskets of peaches. Each basket has 4 red peaches and 3 green peaches. If there are a total of 7 peaches in all baskets. How many baskets of peaches are there?", "qid": "32", "response": "To solve this problem, we need to find the total number of baskets and the total number of peaches.\n\n1. Total number of peaches:\nThere are 4 red peaches and 3 green peaches in each basket. In total, there are 7 peaches.\n\n2. Total number of baskets:\nWe can find the total number of baskets by dividing the total number of peaches by the number of peaches per basket.\n\n7 peaches \u00f7 (4 red peaches + 3 green peaches) = 7 \u00f7 7 = 1.\n\nThe answer is 1 basket of peaches.", "answer": 1.0, "correct": true, "image": "images/svamp/32.png"}