{"question": "During the Arkansas and Texas tech game the Razorback t-shirt shop made $ 215 by selling 5 t-shirts. What is the cost of each t-shirt?", "qid": "593", "response": "To find the cost of each t-shirt, we need to divide the total revenue by the number of t-shirts sold.\n\nRevenue = $215\nNumber of t-shirts sold = 5\n\nCost of each t-shirt = Revenue / Number of t-shirts sold\nCost of each t-shirt = $215 / 5\n\nThe answer is $43.", "answer": 43.0, "correct": true, "image": "images/svamp/593.png"}