{"question": "If Lewis earns $ 1357 every week during the 223 weeks of a harvest season. How much money will he earn if he works for 73 harvest seasons?", "qid": "70", "response": "To solve this problem, we need to find the total amount of money Lewis will earn if he works for 73 harvest seasons.\n\n1. First, we need to convert the number of weeks in a harvest season from 223 to 73.\n\n2. Next, we need to find the total number of weeks Lewis will work in 73 harvest seasons.\n\n73 harvest seasons \\* 223 weeks per harvest season = 166,630 weeks\n\n3. Now, we can find the total amount of money Lewis will earn in 166,630 weeks.\n\n$1357 per week \\* 166,630 weeks = $226,639,900\n\nThe answer is $226,639,900.", "answer": 22090603.0, "correct": false, "image": "images/svamp/70.png"}