{"question": "There are 4 different books and 17 different movies in the ' crazy silly school ' series. If you read 19 of the books and watched 7 of the movies. How many more movies do you still have to watch?", "qid": "825", "response": "To solve this problem, we need to find the total number of books and movies that the person has read and watched.\n\nThere are 4 different books and 17 different movies in the 'crazy silly school' series.\n\nThe person has read 19 books, so we need to find the total number of books they have read.\n\nThe person has watched 7 movies, so we need to find the total number of movies they have watched.\n\nTo find the total number of books and movies, we can add the number of books and movies the person has read and watched.\n\nTotal number of books = 4 + 19 = 23\n\nTotal number of movies = 17 + 7 = 24\n\nNow, we can find the number of more movies the person still has to watch by subtracting the total number of movies they have watched from the total number of movies in the series.\n\nMore movies to watch = 24 - 24 = 0\n\nThe answer is 0.", "answer": 10.0, "correct": false, "image": "images/svamp/825.png"}