{"question": "6 birds and 3 storks were sitting on the fence. 2 more storks came to join them. How many more birds than storks are sitting on the fence?", "qid": "832", "response": "There are 6 birds and 3 storks on the fence initially. After 2 more storks join, there are 6 birds and 5 storks. To find the difference between the number of birds and storks, we can subtract the number of storks from the number of birds.\n\n6 birds - 5 storks = 1 bird\n\nThe answer is 1 bird.", "answer": 1.0, "correct": true, "image": "images/svamp/832.png"}