{"question": "Tommy had some balloons. His mom gave him 34 more balloons for his birthday. Then, Tommy had 60 balloons. How many balloons did Tommy have to start with?", "qid": "106", "response": "To solve this problem, we need to find the number of balloons Tommy had initially. We know that his mom gave him 34 more balloons, so we can add that number to the total number of balloons he had after his birthday.\n\n60 balloons (after birthday) + 34 balloons (given by mom) = 94 balloons (total)\n\nThe answer is 94.", "answer": 26, "correct": false, "image": "images/asdiv/106.png"}