{"question": "Nancy was buying soap for her bathroom. She bought 6 packs with each pack having 5 bars. How many bars of soap did she buy?", "qid": "1601", "response": "To solve this problem, we need to find the total number of bars of soap Nancy bought. We can do this by multiplying the number of packs by the number of bars per pack.\n\nFirst, we need to find the total number of bars per pack. We can do this by multiplying the number of bars per pack by the number of packs.\n\n6 packs x 5 bars per pack = 30 bars per pack\n\nNext, we need to find the total number of bars of soap Nancy bought. We can do this by multiplying the total number of bars per pack by the number of packs.\n\n30 bars per pack x 6 packs = 180 bars of soap\n\nThe answer is 180.", "answer": 30, "correct": true, "image": "images/asdiv/1601.png"}