{"question": "An aquarium had ten fish in it. Later they added three fish. How many fish are in the aquarium now?", "qid": "1918", "response": "First, we need to find the number of fish after the addition of three fish. We can do this by using the equation:\n\nFish added + Fish in aquarium = Total fish\n\nIn this case, 3 fish were added, and there were already 10 fish in the aquarium. So, we can write:\n\n3 + 10 = Total fish\n\nThe total fish in the aquarium now is 13.\n\nThe answer is 13.", "answer": 13, "correct": true, "image": "images/asdiv/1918.png"}