{"question": "Dave was organizing his baseball cards in a binder with eight on each page. If he had three new cards and thirteen old cards to put in the binder, how many pages would he use?", "qid": "1986", "response": "Dave has three new cards and thirteen old cards to put in the binder. He needs to organize them in a way that he can fit eight cards on each page.\n\nFirst, we need to find the total number of cards that Dave has. The total number of cards is 3 (new cards) + 13 (old cards) = 16 cards.\n\nNext, we need to find the total number of pages Dave would need to organize the cards. The total number of pages needed is 16 cards / 8 cards per page = 2 pages.\n\nThe answer is 2 pages.", "answer": 2, "correct": true, "image": "images/asdiv/1986.png"}