{"question": "After the party, Kevin estimated that the total money they spent on food, drinks, and utensils sums up to $560.00. If they spent $268.00 on food and $118.00 on utensils and other stuff, how much did they spend on drinks?", "qid": "339", "response": "To find the amount spent on drinks, we need to subtract the amounts spent on food and utensils from the total amount spent.\n\n$560.00 - $268.00 - $118.00 = $<<560.00-268.00-118.00=174.00>>174.00\n\nThe answer is $174.00.", "answer": 174, "correct": true, "image": "images/asdiv/339.png"}