{"question": "Each bag contains 23 pounds of oranges. How many pounds of oranges are in 45 bags?", "qid": "620", "response": "To solve this problem, we need to find the total weight of oranges in 45 bags. We know that each bag contains 23 pounds of oranges.\n\nFirst, we need to find the total weight of oranges in one bag. To do this, we can multiply the number of pounds in a bag by the number of bags:\n\n23 pounds/bag \\* 45 bags = 1035 pounds\n\nSo, the total weight of oranges in 45 bags is 1035 pounds.\n\nThe answer is 1035 pounds.", "answer": 1035, "correct": true, "image": "images/asdiv/620.png"}