{"question": "It takes 3 eggs to make a cake. How many cakes can you make with 37 eggs?", "qid": "638", "response": "To solve this problem, we need to find the number of cakes that can be made using 37 eggs. Since it takes 3 eggs to make a cake, we can find the number of cakes by dividing the number of eggs by the number of eggs needed to make a cake.\n\n37 eggs \u00f7 3 eggs per cake = 12.3333...\n\nSince we cannot make a fraction of a cake, we need to round up to the nearest whole number of cakes.\n\n12.3333... rounded up to the nearest whole number = 13\n\nThe answer is 13.", "answer": 12, "correct": false, "image": "images/asdiv/638.png"}