{"question": "Kyle bought 3 presents. The first present cost $18. The second present cost $7 more than the first. The third present cost $11 less than the first. How much did Kyle pay for all 3 presents?", "qid": "838", "response": "The first present cost $18. The second present cost $7 more than the first, so it cost $18 + $7 = $<<18+7=25>>25. The third present cost $11 less than the first, so it cost $18 - $11 = $<<18-11=7>>7.\n\nThe total cost for all 3 presents is $25 + $7 + $7 = $<<25+7+7=39>>39.\n\nThe answer is $39.", "answer": 50, "correct": false, "image": "images/asdiv/838.png"}